ozpy/__init__.py
ozpy/base.py
ozpy/exceptions.py
ozpy/mailbox.py
ozpy/zmprov.py
ozpy-0.6.dist-info/DESCRIPTION.rst
ozpy-0.6.dist-info/METADATA
ozpy-0.6.dist-info/RECORD
ozpy-0.6.dist-info/WHEEL
ozpy-0.6.dist-info/metadata.json
ozpy-0.6.dist-info/top_level.txt
