Metadata-Version: 2.0
Name: ozpy
Version: 0.6
Summary: UNKNOWN
Home-page: https://github.com/iomarmochtar/ozpy
Author: Imam Omar Mochtar
Author-email: iomarmochtar@gmail.com
License: GPL
Keywords: Zimbra Python library
Platform: UNKNOWN
Classifier: Development Status :: 4 - Beta
Classifier: Programming Language :: Python :: 2.7
Classifier: Natural Language :: English
Requires-Dist: requests
